pfpsychopy/__init__.py
pfpsychopy/templates/main.py.jinja
pyflies_psychopy-0.2.0.dist-info/LICENSE
pyflies_psychopy-0.2.0.dist-info/METADATA
pyflies_psychopy-0.2.0.dist-info/WHEEL
pyflies_psychopy-0.2.0.dist-info/entry_points.txt
pyflies_psychopy-0.2.0.dist-info/top_level.txt
pyflies_psychopy-0.2.0.dist-info/RECORD
